papamana_django/__init__.py
papamana_django/db.sqlite3
papamana_django/config/__init__.py
papamana_django/config/asgi.py
papamana_django/config/settings.py
papamana_django/config/urls.py
papamana_django/config/utils.py
papamana_django/config/wsgi.py
papamanadjango-0.2.19.dist-info/METADATA
papamanadjango-0.2.19.dist-info/WHEEL
papamanadjango-0.2.19.dist-info/RECORD
