Metadata-Version: 2.3
Name: papamanadjango
Version: 0.2.19
Summary: Module Django and Environtment
Requires-Python: >=3.10
Requires-Dist: django-environ>=0.11.2
Requires-Dist: django==3.2
Requires-Dist: ipython>=8.12.3
Requires-Dist: psycopg2-binary>=2.9.9
Requires-Dist: requests>=2.31.0
